[ {
  "id" : 1,
  "pattern" : "(born",
  "partsOfSpeech" : "VB",
  "index" : {
    "0" : [ "kb=e http://dbpedia.org/ontology/birthDateo", "Coherence=0.169230769230769", "triple=e http://dbpedia.org/ontology/birthDate o", "class=Actor", "{Coherence=0.169230769230769 condAB=0.203703703703704 condBA=1.0 supA=54.0 supAB=11.0 supB=11.0}", "posTag=VB", "interestingness=Coherence", "subject=e", "predicate=http://dbpedia.org/ontology/birthDate", "object=o", "fullPosTag=-LRB-_VBN", "string=dbo:Actor in c_e and exists o : (e& dbo:birthDate& o) in G $> ' (born ' in l_e(c&p&so)" ]
  }
}, {
  "id" : 5,
  "pattern" : "born",
  "partsOfSpeech" : "VB",
  "index" : {
    "0" : [ "kb=e http://dbpedia.org/ontology/birthPlaceo", "Coherence=0.138461538461538", "triple=e http://dbpedia.org/ontology/birthPlace o", "class=Actor", "{Coherence=0.138461538461538 condAB=0.160714285714286 condBA=1.0 supA=56.0 supAB=9.0 supB=9.0}", "posTag=VB", "interestingness=Coherence", "subject=e", "predicate=http://dbpedia.org/ontology/birthPlace", "object=o", "fullPosTag=VBN", "string=dbo:Actor in c_e and exists o : (e& dbo:birthPlace& o) in G $> 'born' in l_e(c&p&so)" ]
  }
}, {
  "id" : 6,
  "pattern" : "died",
  "partsOfSpeech" : "VB",
  "index" : {
    "0" : [ "kb=e http://dbpedia.org/ontology/deathPlaceo", "Coherence=0.15625", "triple=e http://dbpedia.org/ontology/deathPlace o", "class=Actor", "{Coherence=0.15625 condAB=0.185185185185185 condBA=1.0 supA=27.0 supAB=5.0 supB=5.0}", "posTag=VB", "interestingness=Coherence", "subject=e", "predicate=http://dbpedia.org/ontology/deathPlace", "object=o", "fullPosTag=VBD", "string=dbo:Actor in c_e and exists o : (e& dbo:deathPlace& o) in G $> 'died' in l_e(c&p&so)" ]
  }
} ]